{
  "all_time_ranking": [
    {
      "agent": "zone",
      "score": 72.677236,
      "source_share": 0.8308,
      "source_count": 167
    },
    {
      "agent": "sum",
      "score": 49.388193,
      "source_share": 0.8159,
      "source_count": 164
    },
    {
      "agent": "hot",
      "score": 43.400965,
      "source_share": 0.9005,
      "source_count": 181
    },
    {
      "agent": "cycle",
      "score": 36.894922,
      "source_share": 0.8507,
      "source_count": 171
    },
    {
      "agent": "random",
      "score": 13.484201,
      "source_share": 0.8856,
      "source_count": 178
    },
    {
      "agent": "missing",
      "score": 13.410769,
      "source_share": 0.8806,
      "source_count": 177
    },
    {
      "agent": "balanced",
      "score": 11.16646,
      "source_share": 0.8308,
      "source_count": 167
    },
    {
      "agent": "cold",
      "score": 9.302417,
      "source_share": 0.7662,
      "source_count": 154
    }
  ],
  "recent_ranking": [
    {
      "agent": "zone",
      "score": 23.329708,
      "source_share": 0.85,
      "source_count": 17
    },
    {
      "agent": "hot",
      "score": 13.574267,
      "source_share": 0.8,
      "source_count": 16
    },
    {
      "agent": "sum",
      "score": 11.808052,
      "source_share": 0.75,
      "source_count": 15
    },
    {
      "agent": "cycle",
      "score": 10.16109,
      "source_share": 0.7,
      "source_count": 14
    },
    {
      "agent": "random",
      "score": 3.148885,
      "source_share": 0.85,
      "source_count": 17
    },
    {
      "agent": "missing",
      "score": 2.554864,
      "source_share": 0.8,
      "source_count": 16
    },
    {
      "agent": "cold",
      "score": 2.274892,
      "source_share": 0.5,
      "source_count": 10
    },
    {
      "agent": "balanced",
      "score": 1.904121,
      "source_share": 0.7,
      "source_count": 14
    }
  ],
  "delta_ranking": [
    {
      "agent": "cold",
      "recent_score": 2.274892,
      "all_time_score": 9.302417,
      "delta": -7.027525
    },
    {
      "agent": "balanced",
      "recent_score": 1.904121,
      "all_time_score": 11.16646,
      "delta": -9.262339
    },
    {
      "agent": "random",
      "recent_score": 3.148885,
      "all_time_score": 13.484201,
      "delta": -10.335316
    },
    {
      "agent": "missing",
      "recent_score": 2.554864,
      "all_time_score": 13.410769,
      "delta": -10.855905
    },
    {
      "agent": "cycle",
      "recent_score": 10.16109,
      "all_time_score": 36.894922,
      "delta": -26.733832
    },
    {
      "agent": "hot",
      "recent_score": 13.574267,
      "all_time_score": 43.400965,
      "delta": -29.826698
    },
    {
      "agent": "sum",
      "recent_score": 11.808052,
      "all_time_score": 49.388193,
      "delta": -37.580141
    },
    {
      "agent": "zone",
      "recent_score": 23.329708,
      "all_time_score": 72.677236,
      "delta": -49.347528
    }
  ],
  "weight_adjustments": [
    {
      "agent": "cold",
      "delta": -7.027525,
      "weight_delta": 0.0064
    },
    {
      "agent": "balanced",
      "delta": -9.262339,
      "weight_delta": 0.0054
    },
    {
      "agent": "random",
      "delta": -10.335316,
      "weight_delta": 0.005
    },
    {
      "agent": "missing",
      "delta": -10.855905,
      "weight_delta": 0.0048
    },
    {
      "agent": "cycle",
      "delta": -26.733832,
      "weight_delta": -0.0016
    },
    {
      "agent": "hot",
      "delta": -29.826698,
      "weight_delta": -0.0029
    },
    {
      "agent": "sum",
      "delta": -37.580141,
      "weight_delta": -0.006
    },
    {
      "agent": "zone",
      "delta": -49.347528,
      "weight_delta": -0.0108
    }
  ],
  "matrix_ranking": [
    {
      "matrix_type": "22_red_cover_6_to_5",
      "row_id": 3,
      "samples": 6,
      "red_hit_avg": 1.833333,
      "blue_hit_rate": 0.0,
      "hit_rate_ge2": 0.666667,
      "hit_rate_ge3": 0.166667,
      "avg_score": 1.833333
    },
    {
      "matrix_type": "22_red_cover_6_to_5",
      "row_id": 5,
      "samples": 13,
      "red_hit_avg": 1.384615,
      "blue_hit_rate": 0.0,
      "hit_rate_ge2": 0.307692,
      "hit_rate_ge3": 0.230769,
      "avg_score": 1.384615
    },
    {
      "matrix_type": "10_red_guard_6_to_5",
      "row_id": 5,
      "samples": 19,
      "red_hit_avg": 1.263158,
      "blue_hit_rate": 0.0,
      "hit_rate_ge2": 0.421053,
      "hit_rate_ge3": 0.052632,
      "avg_score": 1.263158
    },
    {
      "matrix_type": "10_red_guard_6_to_5",
      "row_id": 2,
      "samples": 19,
      "red_hit_avg": 1.157895,
      "blue_hit_rate": 0.0,
      "hit_rate_ge2": 0.315789,
      "hit_rate_ge3": 0.052632,
      "avg_score": 1.157895
    },
    {
      "matrix_type": "22_red_cover_6_to_5",
      "row_id": 4,
      "samples": 13,
      "red_hit_avg": 1.076923,
      "blue_hit_rate": 0.0,
      "hit_rate_ge2": 0.307692,
      "hit_rate_ge3": 0.076923,
      "avg_score": 1.076923
    },
    {
      "matrix_type": "22_red_cover_6_to_5",
      "row_id": 2,
      "samples": 13,
      "red_hit_avg": 0.923077,
      "blue_hit_rate": 0.076923,
      "hit_rate_ge2": 0.153846,
      "hit_rate_ge3": 0.0,
      "avg_score": 1.038462
    },
    {
      "matrix_type": "10_red_guard_6_to_5",
      "row_id": 3,
      "samples": 19,
      "red_hit_avg": 0.894737,
      "blue_hit_rate": 0.052632,
      "hit_rate_ge2": 0.105263,
      "hit_rate_ge3": 0.0,
      "avg_score": 0.973684
    },
    {
      "matrix_type": "10_red_guard_6_to_5",
      "row_id": 1,
      "samples": 19,
      "red_hit_avg": 0.789474,
      "blue_hit_rate": 0.105263,
      "hit_rate_ge2": 0.052632,
      "hit_rate_ge3": 0.0,
      "avg_score": 0.947368
    },
    {
      "matrix_type": "22_red_cover_6_to_5",
      "row_id": 1,
      "samples": 13,
      "red_hit_avg": 0.923077,
      "blue_hit_rate": 0.0,
      "hit_rate_ge2": 0.230769,
      "hit_rate_ge3": 0.0,
      "avg_score": 0.923077
    },
    {
      "matrix_type": "10_red_guard_6_to_5",
      "row_id": 4,
      "samples": 19,
      "red_hit_avg": 0.789474,
      "blue_hit_rate": 0.052632,
      "hit_rate_ge2": 0.105263,
      "hit_rate_ge3": 0.0,
      "avg_score": 0.868421
    }
  ],
  "suggestions": [
    "建议提高权重倾斜：TOP3=zone,sum,hot（命中贡献累计更高；缺少真实结果时回退为 explain_json 贡献）。",
    "建议降低或观察：BOTTOM3=missing,balanced,cold（命中贡献累计偏低；缺少真实结果时回退为 explain_json 贡献）。",
    "多样性替换触发率：0.00%（越高表示号码集中度越高，可考虑加强多样性惩罚或增加注间差异约束）。",
    "下一步可做自动调参：把 lead_model 权重/learning_rate/decay_gamma 作为变量，按 backtest_report 的 overall 指标网格搜索。"
  ]
}